fujielab/util/launcher/__init__.py
fujielab/util/launcher/config_manager.py
fujielab/util/launcher/create_shortcut.py
fujielab/util/launcher/create_shortcut_macos.py
fujielab/util/launcher/create_shortcut_windows.py
fujielab/util/launcher/debug_util.py
fujielab/util/launcher/i18n.py
fujielab/util/launcher/main_window.py
fujielab/util/launcher/run.py
fujielab/util/launcher/script_runner.py
fujielab/util/launcher/settings_dialog.py
fujielab/util/launcher/shell_runner.py
fujielab/util/launcher/sticky_mdi.py
fujielab/util/launcher/resources/icon.ico
fujielab/util/launcher/resources/icon.png
fujielab/util/launcher/resources/splash.png
fujielab_util_launcher-0.2.2.dist-info/licenses/LICENSE
fujielab_util_launcher-0.2.2.dist-info/METADATA
fujielab_util_launcher-0.2.2.dist-info/WHEEL
fujielab_util_launcher-0.2.2.dist-info/entry_points.txt
fujielab_util_launcher-0.2.2.dist-info/top_level.txt
fujielab_util_launcher-0.2.2.dist-info/RECORD
