Metadata-Version: 2.4
Name: fujielab-util-launcher
Version: 0.2.2
Summary: Fujielab Utility Launcher GUI
Author-email: Shinya Fujie <shinya.fujie@p.chibakoudai.jp>
Maintainer-email: Shinya Fujie <shinya.fujie@p.chibakoudai.jp>
License: Apache-2.0
Project-URL: Homepage, https://github.com/fujielab/fujielab-util-launcher
Project-URL: Bug Tracker, https://github.com/fujielab/fujielab-util-launcher/issues
Project-URL: Documentation, https://github.com/fujielab/fujielab-util-launcher#readme
Project-URL: Source Code, https://github.com/fujielab/fujielab-util-launcher
Keywords: launcher,gui,utility
Classifier: Development Status :: 4 - Beta
Classifier: Intended Audience :: Developers
Classifier: License :: OSI Approved :: Apache Software License
Classifier: Programming Language :: Python :: 3
Classifier: Programming Language :: Python :: 3.8
Classifier: Programming Language :: Python :: 3.9
Classifier: Programming Language :: Python :: 3.10
Classifier: Programming Language :: Python :: 3.11
Classifier: Programming Language :: Python :: 3.12
Classifier: Operating System :: OS Independent
Classifier: Topic :: Utilities
Classifier: Environment :: X11 Applications :: Qt
Requires-Python: >=3.8
License-File: LICENSE
Requires-Dist: PyQt5>=5.15.0
Requires-Dist: PyYAML>=6.0
Dynamic: license-file
